LICENSE
reverse_proxy/__init__.py
reverse_proxy/__main__.py
reverse_proxy/py.typed
python_reverse_proxy-0.0.10.dist-info/LICENSE
python_reverse_proxy-0.0.10.dist-info/METADATA
python_reverse_proxy-0.0.10.dist-info/WHEEL
python_reverse_proxy-0.0.10.dist-info/entry_points.txt
python_reverse_proxy-0.0.10.dist-info/RECORD
